algeb_parser/__init__.py
algeb_parser/parser
algeb_parser/parser.py
algeb_parser-1.0.81.dist-info/LICENSE
algeb_parser-1.0.81.dist-info/METADATA
algeb_parser-1.0.81.dist-info/WHEEL
algeb_parser-1.0.81.dist-info/top_level.txt
algeb_parser-1.0.81.dist-info/RECORD
