Metadata-Version: 2.2
Name: algeb-parser
Version: 1.0.81
Summary: Simple algeb parser
Author: aimergency
License: GNU GPLv3
Platform: any
Requires-Python: >=3.9
License-File: LICENSE
Requires-Dist: dill<1.0.0,>=0.3.9
Requires-Dist: lark<1.3.0,>=1.2.2
Dynamic: author
Dynamic: description
Dynamic: description-content-type
Dynamic: license
Dynamic: platform
Dynamic: requires-dist
Dynamic: requires-python
Dynamic: summary
